{"0": "Interior Services Animations", "1": "Ranking & Leaderboard", "2": "Partner Storefront & Sections", "3": "Partner Landing Studio", "4": "Storefront Tutorial Flow", "5": "Bulk Product Import", "6": "User Profile Page", "7": "Product Pricing & Performance", "8": "Wallet & Credits", "9": "Login & Auth", "10": "Superadmin Dashboard", "11": "Admin Orders", "12": "Content Manager", "13": "KYC Verification", "14": "ZQ Pricing Modal", "15": "Add Product Modal", "16": "Edit Product Modal", "17": "Admin User Settings", "18": "Supplier & Guest Orders", "19": "Shop Builder Studio", "20": "Admin Inquiry & Service", "21": "Supplier Orders Page", "22": "Category Add Modal", "23": "Products Table", "24": "Activity Logs", "25": "AI Support Chat", "26": "Product Info & Variants", "27": "Supplier Chat", "28": "Brand By-Brand Page", "29": "Members Table", "30": "Order Cards & Icons", "31": "Products Page Main", "32": "Supplier Demo", "33": "Encashment Page", "34": "Layout Navbar & Promo", "35": "Partner Subscriptions", "36": "Profile Wallet Tab", "37": "Auth Forgot Password", "38": "ZQ Product Preview", "39": "Category List Products", "40": "Components Group 40", "41": "Components Group 41", "42": "Components Group 42", "43": "Dynamicnotify Group 43", "44": "Webpages Group 44", "45": "Components Group 45", "46": "Customer Group 46", "47": "Products Group 47", "48": "Project Group 48", "49": "Shipping Group 49", "50": "Dashboard Group 50", "51": "Profile Group 51", "52": "Products Group 52", "53": "Ai Group 53", "54": "Assembly Group 54", "55": "Components Group 55", "56": "Globalproduct Group 56", "57": "Landing Group 57", "58": "Partner Group 58", "59": "Partner Group 59", "60": "Product Group 60", "61": "Reports Group 61", "62": "Supplier Group 62", "63": "Supplier Group 63", "64": "Ai Group 64", "65": "Components Group 65", "66": "Customer Group 66", "67": "Dashboard Group 67", "68": "Item Group 68", "69": "Landing Group 69", "70": "Landing Group 70", "71": "Landing Group 71", "72": "Members Group 72", "73": "Members Group 73", "74": "Products Group 74", "75": "Products Group 75", "76": "Ai Group 76", "77": "Auth Group 77", "78": "Buttons Group 78", "79": "Components Group 79", "80": "Supplier Group 80", "81": "Supplier Group 81", "82": "Accounting Group 82", "83": "Landing Group 83", "84": "Orders Group 84", "85": "Partner Group 85", "86": "Profile Group 86", "87": "Accounting Group 87", "88": "Auth Group 88", "89": "Brands Group 89", "90": "Dashboard Group 90", "91": "Media Group 91", "92": "Partner Group 92", "93": "Products Group 93", "94": "Products Group 94", "95": "Profile Group 95", "96": "Profile Group 96", "97": "Profile Group 97", "98": "Profile Group 98", "99": "Project Group 99", "100": "Accounting Group 100", "101": "Accounting Group 101", "102": "Dashboard Group 102", "103": "Expenses Group 103", "104": "Globalproduct Group 104", "105": "Payments Group 105", "106": "Products Group 106", "107": "Products Group 107", "108": "Products Group 108", "109": "Profile Group 109", "110": "Ui Group 110", "111": "Webpages Group 111", "112": "Webpages Group 112", "113": "Auth Group 113", "114": "Branches Group 114", "115": "Buttons Group 115", "116": "Buttons Group 116", "117": "Profile Group 117", "118": "Profile Group 118", "119": "Accounting Group 119", "120": "Apps Group 120", "121": "Components Group 121", "122": "Partner Group 122", "123": "Payments Group 123", "124": "Product Group 124", "125": "Product Group 125", "126": "Supplier Group 126", "127": "Verification Group 127", "128": "Webpages Group 128", "129": "Auth Group 129", "130": "Buttons Group 130", "131": "Components Group 131", "132": "Customer Group 132", "133": "Dashboard Group 133", "134": "Emailblast Group 134", "135": "Interiorrequests Group 135", "136": "Item Group 136", "137": "Landing Group 137", "138": "Members Group 138", "139": "Products Group 139", "140": "Products Group 140", "141": "Products Group 141", "142": "Profile Group 142", "143": "Accounting Group 143", "144": "Accounting Group 144", "145": "Ai Group 145", "146": "Auth Group 146", "147": "Expenses Group 147", "148": "Item Group 148", "149": "Landing Group 149", "150": "Payments Group 150", "151": "Products Group 151", "152": "Profile Group 152", "153": "Settings Group 153", "154": "Supplier Group 154", "155": "Supplier Group 155", "156": "Webpages Group 156", "157": "Webpages Group 157", "158": "Webpages Group 158", "159": "Accounting Group 159", "160": "Chat Group 160", "161": "Chat Group 161", "162": "Customer Group 162", "163": "Dashboard Group 163", "164": "Dashboard Group 164", "165": "Faq Group 165", "166": "Landing Group 166", "167": "Product Group 167", "168": "Superadmin Group 168", "169": "Supplier Group 169", "170": "Templates Group 170", "171": "Accounting Group 171", "172": "Landing Group 172", "173": "Landing Group 173", "174": "Layout Group 174", "175": "Members Group 175", "176": "Product Group 176", "177": "Products Group 177", "178": "Products Group 178", "179": "Products Group 179", "180": "Superadmin Group 180", "181": "Templates Group 181", "182": "Templates Group 182", "183": "Templates Group 183", "184": "Ui Group 184", "185": "Verification Group 185", "186": "Integrations Group 186", "187": "Partner Group 187", "188": "Product Group 188", "189": "Products Group 189", "190": "Products Group 190", "191": "Products Group 191", "192": "Products Group 192", "193": "Profile Group 193", "194": "Profile Group 194", "195": "Profile Group 195", "196": "Referrals Group 196", "197": "Sections Group 197", "198": "Settings Group 198", "199": "Settings Group 199", "200": "Supplier Group 200", "201": "Apps Group 201", "202": "Category Group 202"}